tdsc/__init__.py
tdsc/context.py
tdsc/state.py
tdsc/strategy.py
tdsc/utils/__init__.py
tdsc/utils/git.py
tdsc-0.1.2.dist-info/WHEEL
tdsc-0.1.2.dist-info/METADATA
tdsc-0.1.2.dist-info/RECORD
