Metadata-Version: 2.1
Name: tdsc
Version: 0.1.2
Summary: 
Home-page: https://github.com/liamdawson/tdsc
License: MIT
Author: Liam Dawson
Author-email: liam@ldaws.com
Requires-Python: >=2.7
Classifier: License :: OSI Approved :: MIT License
Classifier: Programming Language :: Python :: 2
Classifier: Programming Language :: Python :: 2.7
Classifier: Programming Language :: Python :: 3
Classifier: Programming Language :: Python :: 3.4
Classifier: Programming Language :: Python :: 3.5
Classifier: Programming Language :: Python :: 3.6
Classifier: Programming Language :: Python :: 3.7
Requires-Dist: appdirs (>=1.4,<2.0)
Requires-Dist: distro (>=1.3,<2.0)
Requires-Dist: six (>=1.11,<1.12)
Requires-Dist: toml (>=0.9,<0.10)
